pytnm/__init__.py
pytnm/barrier.py
pytnm/utils/__init__.py
pytnm/utils/conversion.py
pytnm/utils/geom.py
pytnm/utils/model.py
pytnm/utils/stamina.py
pytnm/utils/template.py
pytnm/utils/validation.py
pytnm/utils/report/__init__.py
pytnm/utils/report/base.py
pytnm-1.1.dist-info/LICENSE
pytnm-1.1.dist-info/METADATA
pytnm-1.1.dist-info/WHEEL
pytnm-1.1.dist-info/top_level.txt
pytnm-1.1.dist-info/RECORD
