Metadata-Version: 2.1
Name: pytnm
Version: 1.1
Summary: FHWA TNM 2.5 Geospatial Toolkit
Home-page: https://github.com/fstraw/pytnm
Author: Brandon Batt
Author-email: brbatt@gmail.com
License: MIT
Platform: UNKNOWN
Classifier: License :: OSI Approved :: MIT License
Classifier: Programming Language :: Python :: 3
Classifier: Programming Language :: Python :: 3.7
License-File: LICENSE
Requires-Dist: openpyxl
Requires-Dist: pyshp
